LICENSE
MANIFEST.in
README.md
pyproject.toml
setup.cfg
setup.py
adminlte2_pdq/__init__.py
adminlte2_pdq/admin_menu.py
adminlte2_pdq/constants.py
adminlte2_pdq/decorators.py
adminlte2_pdq/forms.py
adminlte2_pdq/menu.py
adminlte2_pdq/middleware.py
adminlte2_pdq/mixins.py
adminlte2_pdq/urls.py
adminlte2_pdq/views.py
adminlte2_pdq/static/adminlte2_pdq/conflicts/conflicts.css
adminlte2_pdq/static/adminlte2_pdq/conflicts/conflicts.js
adminlte2_pdq/static/adminlte2_pdq/conflicts/django-admin-conflicts.css
adminlte2_pdq/static/adminlte2_pdq/extra-features/extra-features.css
adminlte2_pdq/static/adminlte2_pdq/extra-features/extra-features.js
adminlte2_pdq/static/adminlte2_pdq/extra-features/header-breadcrumb-overlap-fix.css
adminlte2_pdq/static/adminlte2_pdq/extra-features/header-breadcrumb-overlap-fix.js
adminlte2_pdq/static/adminlte2_pdq/extra-features/sidebar-state.js
adminlte2_pdq/static/third-party/admin-lte/2.3.7/css/AdminLTE.css
adminlte2_pdq/static/third-party/admin-lte/2.3.7/css/AdminLTE.min.css
adminlte2_pdq/static/third-party/admin-lte/2.3.7/css/skins/_all-skins.css
adminlte2_pdq/static/third-party/admin-lte/2.3.7/css/skins/_all-skins.min.css
adminlte2_pdq/static/third-party/admin-lte/2.3.7/css/skins/skin-black-light.css
adminlte2_pdq/static/third-party/admin-lte/2.3.7/css/skins/skin-black-light.min.css
adminlte2_pdq/static/third-party/admin-lte/2.3.7/css/skins/skin-black.css
adminlte2_pdq/static/third-party/admin-lte/2.3.7/css/skins/skin-black.min.css
adminlte2_pdq/static/third-party/admin-lte/2.3.7/css/skins/skin-blue-light.css
adminlte2_pdq/static/third-party/admin-lte/2.3.7/css/skins/skin-blue-light.min.css
adminlte2_pdq/static/third-party/admin-lte/2.3.7/css/skins/skin-blue.css
adminlte2_pdq/static/third-party/admin-lte/2.3.7/css/skins/skin-blue.min.css
adminlte2_pdq/static/third-party/admin-lte/2.3.7/css/skins/skin-green-light.css
adminlte2_pdq/static/third-party/admin-lte/2.3.7/css/skins/skin-green-light.min.css
django_adminlte2_pdq.egg-info/PKG-INFO
django_adminlte2_pdq.egg-info/SOURCES.txt
django_adminlte2_pdq.egg-info/dependency_links.txt
django_adminlte2_pdq.egg-info/requires.txt
django_adminlte2_pdq.egg-info/top_level.txt
